{
  "total_steps": 78,
  "metrics": {
    "distance_to_goal": "0.11285927146673203",
    "success": "1.0",
    "spl": 0.988,
    "distance_to_goal_reward": "-0.0"
  },
  "gps_trace": [
    {
      "step": 1,
      "distance": 10.9006
    },
    {
      "step": 2,
      "distance": 10.9006
    },
    {
      "step": 3,
      "distance": 10.9006
    },
    {
      "step": 4,
      "distance": 10.9006
    },
    {
      "step": 5,
      "distance": 10.9006
    },
    {
      "step": 6,
      "distance": 10.9006
    },
    {
      "step": 7,
      "distance": 10.9006
    },
    {
      "step": 8,
      "distance": 10.9006
    },
    {
      "step": 9,
      "distance": 10.9006
    },
    {
      "step": 10,
      "distance": 10.9006
    },
    {
      "step": 11,
      "distance": 10.9006
    },
    {
      "step": 12,
      "distance": 10.9006
    },
    {
      "step": 13,
      "distance": 10.9006
    },
    {
      "step": 14,
      "distance": 10.9006
    },
    {
      "step": 15,
      "distance": 10.9006
    },
    {
      "step": 16,
      "distance": 10.9006
    },
    {
      "step": 17,
      "distance": 10.9006
    },
    {
      "step": 18,
      "distance": 10.9006
    },
    {
      "step": 19,
      "distance": 10.905
    },
    {
      "step": 20,
      "distance": 10.905
    }
  ]
}